open_source_fpga_environment/CALCULADORA/Receptor/src/design/bcd_to_7seg.sv
module bcd_to_7seg (
    input  wire [3:0] digit,
    output reg  [6:0] seg    // seg[6]=a, seg[5]=b, ..., seg[0]=g
);

always_comb begin
    seg = 7'b1111111;
end

endmodule

open_source_fpga_environment/CALCULADORA/Receptor/src/sim/bcd_to_7seg_tb.sv
module bcd_to_7seg_tb;

reg [3:0] digit;
wire [6:0] seg;

bcd_to_7seg dut (
    .digit(digit),
    .seg(seg)
);

initial begin
    $dumpfile("bcd_to_7seg_tb.vcd");
    $dumpvars(0, bcd_to_7seg_tb);
    
    $display("BCD to 7-Seg Pattern Verification");
    $display("digit | seg[6:0] (binary) | Expected | Status");
    $display("------|------------------|----------|--------");
    
    // Prueba cada dígito
    for (digit = 0; digit <= 9; digit = digit + 1) begin
        #1;
        case (digit)
            0: $display("  %d   | %b       |  1111110 | %s", digit, seg, (seg == 7'b1111110) ? "OK" : "FAIL");
            1: $display("  %d   | %b       |  0110000 | %s", digit, seg, (seg == 7'b0110000) ? "OK" : "FAIL");
            2: $display("  %d   | %b       |  1101101 | %s", digit, seg, (seg == 7'b1101101) ? "OK" : "FAIL");
            3: $display("  %d   | %b       |  1111001 | %s", digit, seg, (seg == 7'b1111001) ? "OK" : "FAIL");
            4: $display("  %d   | %b       |  0110011 | %s", digit, seg, (seg == 7'b0110011) ? "OK" : "FAIL");
            5: $display("  %d   | %b       |  1011011 | %s", digit, seg, (seg == 7'b1011011) ? "OK" : "FAIL");
            6: $display("  %d   | %b       |  1011111 | %s", digit, seg, (seg == 7'b1011111) ? "OK" : "FAIL");
            7: $display("  %d   | %b       |  1110000 | %s", digit, seg, (seg == 7'b1110000) ? "OK" : "FAIL");
            8: $display("  %d   | %b       |  1111111 | %s", digit, seg, (seg == 7'b1111111) ? "OK" : "FAIL");
            9: $display("  %d   | %b       |  1111011 | %s", digit, seg, (seg == 7'b1111011) ? "OK" : "FAIL");
        endcase
    end
    
    #1;
    $finish;
end

endmodule

open_source_fpga_environment/CALCULADORA/Receptor/src/sim/bcd_to_7seg_tb.vcd
$date
	Thu Apr 30 11:53:24 2026
$end
$version
	Icarus Verilog
$end
$timescale
	1s
$end
$scope module bcd_to_7seg_tb $end
$var wire 7 ! seg [6:0] $end
$var reg 4 " digit [3:0] $end
$scope module dut $end
$var wire 4 # digit [3:0] $end
$var reg 7 $ seg [6:0] $end
$upscope $end
$upscope $end
$enddefinitions $end
$comment Show the parameter values. $end
$dumpall
$end
#0
$dumpvars
b1111110 $
b0 #
b0 "
b1111110 !
$end
#1
b110000 !
b110000 $
b1 "
b1 #
#2
b1101101 !
b1101101 $
b10 "
b10 #
#3
b1111001 !
b1111001 $
b11 "
b11 #
#4
b110011 !
b110011 $
b100 "
b100 #
#5
b1011011 !
b1011011 $
b101 "
b101 #
#6
b1011111 !
b1011111 $
b110 "
b110 #
#7
b1110000 !
b1110000 $
b111 "
b111 #
#8
b1111111 !
b1111111 $
b1000 "
b1000 #
#9
b1111011 !
b1111011 $
b1001 "
b1001 #
#10
b0 !
b0 $
b1010 "
b1010 #
